[
   { 
     "id": 80, 
     "imageUrl": "/men/accessories/accessories1.webp", 
     "title": "SPRAY WATERTIGHT BAG L",
     "color": "CARBON", 
     "price": 4200,
     "quantity": 1,
     "sizes" : [
      { "size_id": 1, "size_name": "XS" },
      { "size_id": 2, "size_name": "S" },
      { "size_id": 3, "size_name": "M" },
      { "size_id": 4, "size_name": "L" },
      { "size_id": 5, "size_name": "XL" },
      { "size_id": 6, "size_name": "XXL" }
    ]  
    },
    { 
      "id": 81, 
      "imageUrl": "/men/accessories/accessories2.webp", 
      "title": "SPRAY WATERTIGHT BAG S", 
      "color": "CARBON", 
      "price": 4200,
      "quantity": 1,
      "sizes" : [
        { "size_id": 1, "size_name": "XS" },
        { "size_id": 2, "size_name": "S" },
        { "size_id": 3, "size_name": "M" },
        { "size_id": 4, "size_name": "L" },
        { "size_id": 5, "size_name": "XL" },
        { "size_id": 6, "size_name": "XXL" }
      ]  

    },
    { 
      "id": 82, 
      "imageUrl": "/men/accessories/accessories3.webp", 
      "title": "SPRAY WATERTIGHT BACKPACK", 
      "color": "CARBON", 
      "price": 4200,
      "quantity": 1,
      "sizes" : [
        { "size_id": 1, "size_name": "XS" },
        { "size_id": 2, "size_name": "S" },
        { "size_id": 3, "size_name": "M" },
        { "size_id": 4, "size_name": "L" },
        { "size_id": 5, "size_name": "XL" },
        { "size_id": 6, "size_name": "XXL" }
      ]

    },
    { "id": 83, 
      "imageUrl": "/men/accessories/accessories4.webp", 
      "title": "SPRAY WATERTIGHT BACKPACK", 
      "color": "NAVY", 
      "price": 4200,
      "quantity": 1,
      "sizes" : [
        { "size_id": 1, "size_name": "XS" },
        { "size_id": 2, "size_name": "S" },
        { "size_id": 3, "size_name": "M" },
        { "size_id": 4, "size_name": "L" },
        { "size_id": 5, "size_name": "XL" },
        { "size_id": 6, "size_name": "XXL" }
      ]  
    },
    {
      "id": 84, 
      "imageUrl": "/men/accessories/accessories5.webp", 
      "title": "RACE 70 DM3 DUFFEL BAG", 
      "color": "NAVY", 
      "price": 4200,
      "quantity": 1,
      "sizes" : [
        { "size_id": 1, "size_name": "XS" },
        { "size_id": 2, "size_name": "S" },
        { "size_id": 3, "size_name": "M" },
        { "size_id": 4, "size_name": "L" },
        { "size_id": 5, "size_name": "XL" },
        { "size_id": 6, "size_name": "XXL" }
      ]
    },
    { 
      "id": 85, 
      "imageUrl": "/men/accessories/accessories6.webp", 
      "title": "DELTA CABIN BAG", 
      "color": "NAVY",
      "price": 4200,
       "quantity": 1,
      "sizes" : [
        { "size_id": 1, "size_name": "XS" },
        { "size_id": 2, "size_name": "S" },
        { "size_id": 3, "size_name": "M" },
        { "size_id": 4, "size_name": "L" },
        { "size_id": 5, "size_name": "XL" },
        { "size_id": 6, "size_name": "XXL" }
      ] 
    },
    { 
      "id": 86, 
      "imageUrl": "/men/accessories/accessories7.webp", 
      "title": "DELTA TROLLEY BAG", 
      "color": "NAVY", 
      "price": 4200,
       "quantity": 1,
      "sizes" : [
        { "size_id": 1, "size_name": "XS" },
        { "size_id": 2, "size_name": "S" },
        { "size_id": 3, "size_name": "M" },
        { "size_id": 4, "size_name": "L" },
        { "size_id": 5, "size_name": "XL" },
        { "size_id": 6, "size_name": "XXL" }
      ]
    },
    { 
      "id": 87, 
      "imageUrl": "/men/accessories/accessories8.webp", 
      "title": "SPRAY DUFFEL L", 
      "color": "DIM GREY", 
      "price": 4200,
       "quantity": 1,
      "sizes" : [
        { "size_id": 1, "size_name": "XS" },
        { "size_id": 2, "size_name": "S" },
        { "size_id": 3, "size_name": "M" },
        { "size_id": 4, "size_name": "L" },
        { "size_id": 5, "size_name": "XL" },
        { "size_id": 6, "size_name": "XXL" }
      ]
    },
    { 
      "id": 88,
      "imageUrl": "/men/accessories/accessories9.webp", 
      "title": "SPRAY DUFFEL L", 
      "color": "ASPHALT", 
      "price": 4200,
       "quantity": 1,
      "sizes" : [
        { "size_id": 1, "size_name": "XS" },
        { "size_id": 2, "size_name": "S" },
        { "size_id": 3, "size_name": "M" },
        { "size_id": 4, "size_name": "L" },
        { "size_id": 5, "size_name": "XL" },
        { "size_id": 6, "size_name": "XXL" }
      ] 
    },
    { 
      "id": 89, 
      "imageUrl": "/men/accessories/accessories10.webp", 
      "title": "SPRAY DUFFEL L", 
      "color": "CARBON", 
      "price": 4200,
       "quantity": 1,
      "sizes" : [
        { "size_id": 1, "size_name": "XS" },
        { "size_id": 2, "size_name": "S" },
        { "size_id": 3, "size_name": "M" },
        { "size_id": 4, "size_name": "L" },
        { "size_id": 5, "size_name": "XL" },
        { "size_id": 6, "size_name": "XXL" }
      ]
    },
    {
        "id": 90, 
        "imageUrl": "/men/accessories/accessories11.webp", 
        "title": "SPRAY DUFFEL L", 
        "color": "DIM GREY", 
        "price": 4200,
         "quantity": 1,
        "sizes" : [
            { "size_id": 1, "size_name": "XS" },
            { "size_id": 2, "size_name": "S" },
            { "size_id": 3, "size_name": "M" },
            { "size_id": 4, "size_name": "L" },
            { "size_id": 5, "size_name": "XL" },
            { "size_id": 6, "size_name": "XXL" }
          ]
    }
]